QuarticSolver.cpython-35m-i386-linux-gnu.so
QuarticSolver-0.1.5.dist-info/RECORD
QuarticSolver-0.1.5.dist-info/METADATA
QuarticSolver-0.1.5.dist-info/top_level.txt
QuarticSolver-0.1.5.dist-info/LICENSE
QuarticSolver-0.1.5.dist-info/WHEEL
