Metadata-Version: 2.1
Name: QuarticSolver
Version: 0.1.5
Summary: A CPU/GPU library for finding the minimum of a quartic function
Home-page: https://github.com/qureshizawar/CUDA-quartic-solver
Author: Zawar Qureshi
Author-email: qureshizawar@gmail.com
License: UNKNOWN
Keywords: CUDA,QUARTIC,OPTIMISATION
Platform: UNKNOWN
Classifier: Development Status :: 3 - Alpha
Classifier: Intended Audience :: Developers
Classifier: Topic :: Software Development
Classifier: License :: OSI Approved :: MIT License
Classifier: Programming Language :: Python :: 3.6
Requires-Dist: numpy
